finetuning_scheduler/__about__.py
finetuning_scheduler/__init__.py
finetuning_scheduler/fts.py
finetuning_scheduler/fts_supporters.py
finetuning_scheduler/py.typed
finetuning_scheduler/setup_tools.py
finetuning_scheduler/types.py
finetuning_scheduler/dynamic_versioning/__init__.py
finetuning_scheduler/dynamic_versioning/toggle_lightning_mode.py
finetuning_scheduler/dynamic_versioning/utils.py
finetuning_scheduler/strategy_adapters/__init__.py
finetuning_scheduler/strategy_adapters/_wrap_utils.py
finetuning_scheduler/strategy_adapters/base.py
finetuning_scheduler/strategy_adapters/fsdp.py
finetuning_scheduler/strategy_adapters/model_parallel.py
finetuning_scheduler-2.10.0.dist-info/licenses/LICENSE
fts_examples/__init__.py
fts_examples/cfg_utils.py
fts_examples/cli_experiment_utils.py
fts_examples/fts_superglue.py
fts_examples/config/RteBoolqModule_ft_schedule_deberta_base.yaml
fts_examples/config/RteBoolqModule_ft_schedule_deberta_base_fsdp.yaml
fts_examples/config/fts_defaults.yaml
fts_examples/config/fts_explicit.yaml
fts_examples/config/fts_implicit.yaml
fts_examples/config/nofts_baseline.yaml
fts_examples/config/advanced/fsdp/fts_ddp_fsdp_baseline_profile.yaml
fts_examples/config/advanced/fsdp/fts_fsdp_awp_overrides_offload_profile.yaml
fts_examples/config/advanced/fsdp/fts_fsdp_awp_overrides_profile.yaml
fts_examples/config/advanced/fsdp/fts_fsdp_basic_profile.yaml
fts_examples/config/advanced/reinit_lr/explicit_reinit_lr.yaml
fts_examples/config/advanced/reinit_lr/fts_explicit_reinit_lr.yaml
fts_examples/config/advanced/reinit_lr/fts_implicit_reinit_lr.yaml
fts_examples/config/advanced/reinit_optim_lr/explicit_reinit_optim_lr.yaml
fts_examples/config/advanced/reinit_optim_lr/fts_explicit_reinit_optim_lr.yaml
fts_examples/config/advanced/reinit_optim_lr/fts_implicit_reinit_optim_lr.yaml
fts_examples/config/advanced/reinit_optim_lr/fts_implicit_reinit_optim_lr_use_curr.yaml
fts_examples/model_parallel/mp_examples.py
fts_examples/model_parallel/torchtitan_llama.py
finetuning_scheduler-2.10.0.dist-info/METADATA
finetuning_scheduler-2.10.0.dist-info/WHEEL
finetuning_scheduler-2.10.0.dist-info/entry_points.txt
finetuning_scheduler-2.10.0.dist-info/top_level.txt
finetuning_scheduler-2.10.0.dist-info/RECORD
