Metadata-Version: 2.4
Name: finetuning-scheduler
Version: 2.10.0
Summary: A PyTorch Lightning extension that enhances model experimentation with flexible fine-tuning schedules.
Author-email: Daniel Dale <danny.dale@gmail.com>
License-Expression: Apache-2.0
Project-URL: Homepage, https://github.com/speediedan/finetuning-scheduler
Project-URL: Bug Tracker, https://github.com/speediedan/finetuning-scheduler/issues
Project-URL: Documentation, https://finetuning-scheduler.readthedocs.io/en/stable/
Project-URL: Source Code, https://github.com/speediedan/finetuning-scheduler
Keywords: deep learning,pytorch,AI,machine learning,pytorch-lightning,lightning,fine-tuning,finetuning
Classifier: Environment :: Console
Classifier: Natural Language :: English
Classifier: Development Status :: 5 - Production/Stable
Classifier: Intended Audience :: Developers
Classifier: Topic :: Scientific/Engineering :: Artificial Intelligence
Classifier: Topic :: Scientific/Engineering :: Image Recognition
Classifier: Topic :: Scientific/Engineering :: Information Analysis
Classifier: Operating System :: OS Independent
Classifier: Programming Language :: Python :: 3
Classifier: Programming Language :: Python :: 3.10
Classifier: Programming Language :: Python :: 3.11
Classifier: Programming Language :: Python :: 3.12
Classifier: Programming Language :: Python :: 3.13
Requires-Python: >=3.10
License-File: LICENSE
Requires-Dist: torch>=2.6.0
Requires-Dist: lightning<2.6.1,>=2.6.0
Provides-Extra: cli
Requires-Dist: jsonargparse[signatures]>=4.27.7; extra == "cli"
Requires-Dist: omegaconf>=2.2.3; extra == "cli"
Requires-Dist: hydra-core>=1.2.0; extra == "cli"
Provides-Extra: extra
Requires-Dist: rich>=12.3.0; extra == "extra"
Requires-Dist: jsonargparse[signatures]>=4.27.7; extra == "extra"
Requires-Dist: omegaconf>=2.2.3; extra == "extra"
Requires-Dist: hydra-core>=1.2.0; extra == "extra"
Provides-Extra: examples
Requires-Dist: datasets>=4.0.0; extra == "examples"
Requires-Dist: evaluate>=0.3.0; extra == "examples"
Requires-Dist: transformers>=4.26.0; extra == "examples"
Requires-Dist: scikit-learn>=1.2.0; extra == "examples"
Requires-Dist: sentencepiece>=0.2.0; extra == "examples"
Requires-Dist: tensorboardX>=2.6.1; extra == "examples"
Requires-Dist: tabulate>=0.8.9; extra == "examples"
Requires-Dist: psutil>=5.9.0; extra == "examples"
Requires-Dist: pip>=21.0.0; extra == "examples"
Requires-Dist: jsonargparse[signatures]>=4.27.7; extra == "examples"
Requires-Dist: omegaconf>=2.2.3; extra == "examples"
Requires-Dist: hydra-core>=1.2.0; extra == "examples"
Provides-Extra: ipynb
Requires-Dist: ipython>=7.10.0; extra == "ipynb"
Requires-Dist: jupytext>=1.10.0; extra == "ipynb"
Requires-Dist: nbval>=0.9.6; extra == "ipynb"
Requires-Dist: notebook>=6.4.0; extra == "ipynb"
Requires-Dist: nbformat>=5.0.0; extra == "ipynb"
Requires-Dist: nbclient>=0.5.0; extra == "ipynb"
Requires-Dist: nbconvert>=6.0.0; extra == "ipynb"
Requires-Dist: jupyter-client>=7.0.0; extra == "ipynb"
Requires-Dist: jupyter-core>=4.8.0; extra == "ipynb"
Requires-Dist: ipykernel>=6.0.0; extra == "ipynb"
Requires-Dist: ipywidgets>=7.6.0; extra == "ipynb"
Requires-Dist: traitlets>=5.0.0; extra == "ipynb"
Provides-Extra: all
Requires-Dist: rich>=12.3.0; extra == "all"
Requires-Dist: jsonargparse[signatures]>=4.27.7; extra == "all"
Requires-Dist: omegaconf>=2.2.3; extra == "all"
Requires-Dist: hydra-core>=1.2.0; extra == "all"
Requires-Dist: datasets>=4.0.0; extra == "all"
Requires-Dist: evaluate>=0.3.0; extra == "all"
Requires-Dist: transformers>=4.26.0; extra == "all"
Requires-Dist: scikit-learn>=1.2.0; extra == "all"
Requires-Dist: sentencepiece>=0.2.0; extra == "all"
Requires-Dist: tensorboardX>=2.6.1; extra == "all"
Requires-Dist: tabulate>=0.8.9; extra == "all"
Requires-Dist: psutil>=5.9.0; extra == "all"
Requires-Dist: pip>=21.0.0; extra == "all"
Requires-Dist: ipython>=7.10.0; extra == "all"
Requires-Dist: jupytext>=1.10.0; extra == "all"
Requires-Dist: nbval>=0.9.6; extra == "all"
Requires-Dist: notebook>=6.4.0; extra == "all"
Requires-Dist: nbformat>=5.0.0; extra == "all"
Requires-Dist: nbclient>=0.5.0; extra == "all"
Requires-Dist: nbconvert>=6.0.0; extra == "all"
Requires-Dist: jupyter-client>=7.0.0; extra == "all"
Requires-Dist: jupyter-core>=4.8.0; extra == "all"
Requires-Dist: ipykernel>=6.0.0; extra == "all"
Requires-Dist: ipywidgets>=7.6.0; extra == "all"
Requires-Dist: traitlets>=5.0.0; extra == "all"
Dynamic: description
Dynamic: description-content-type
Dynamic: license-file
Dynamic: requires-dist
Dynamic: summary
